{
  "recentFiles": [
    {
      "basename": "05_Back_2309 일곱 난쟁이",
      "path": "코딩 테스트 강의/1주차/05_Back_2309 일곱 난쟁이.md"
    },
    {
      "basename": "무제 파일",
      "path": "무제 파일.canvas"
    },
    {
      "basename": "10844_쉬운 계단 수",
      "path": "코딩 테스트/백준/10844_쉬운 계단 수.md"
    },
    {
      "basename": "1463_1로 만들기",
      "path": "코딩 테스트/백준/1463_1로 만들기.md"
    },
    {
      "basename": "2579_계단 오르기",
      "path": "코딩 테스트/백준/2579_계단 오르기.md"
    },
    {
      "basename": "1932_정수 삼각형",
      "path": "코딩 테스트/백준/1932_정수 삼각형.md"
    },
    {
      "basename": "1149_RGB 거리",
      "path": "코딩 테스트/백준/1149_RGB 거리.md"
    },
    {
      "basename": "1912_연속합",
      "path": "코딩 테스트/백준/1912_연속합.md"
    },
    {
      "basename": "9461_파도반 수열",
      "path": "코딩 테스트/백준/9461_파도반 수열.md"
    },
    {
      "basename": "1904_01타일",
      "path": "코딩 테스트/백준/1904_01타일.md"
    },
    {
      "basename": "9184_신나는 함수 실행",
      "path": "코딩 테스트/백준/9184_신나는 함수 실행.md"
    },
    {
      "basename": "24416_알고리즘 수업 - 피보나치 수 1",
      "path": "코딩 테스트/백준/24416_알고리즘 수업 - 피보나치 수 1.md"
    },
    {
      "basename": "2580_스도쿠",
      "path": "코딩 테스트/백준/2580_스도쿠.md"
    },
    {
      "basename": "9663_N-Queen",
      "path": "코딩 테스트/백준/9663_N-Queen.md"
    }
  ],
  "omittedPaths": []
}